usau_scraper/__init__.py
usau_scraper/__main__.py
usau_scraper/rankingScraper.py
usau_scraper/teamScraper.py
usau_scraper/tournamentScraper.py
usau_scraper/tests/test_all.py
usau_scraper/usau_scraper.egg-info/PKG-INFO
usau_scraper/usau_scraper.egg-info/SOURCES.txt
usau_scraper/usau_scraper.egg-info/dependency_links.txt
usau_scraper/usau_scraper.egg-info/requires.txt
usau_scraper/usau_scraper.egg-info/top_level.txt
usau_scraper-0.4.0.dist-info/LICENSE
usau_scraper-0.4.0.dist-info/METADATA
usau_scraper-0.4.0.dist-info/WHEEL
usau_scraper-0.4.0.dist-info/top_level.txt
usau_scraper-0.4.0.dist-info/RECORD
